{"frames": [

{
	"filename": "FailBoard.png",
	"frame": {"x":1,"y":1,"w":262,"h":250},
	"rotated": false,
	"trimmed": true,
	"spriteSourceSize": {"x":668,"y":274,"w":262,"h":250},
	"sourceSize": {"w":1600,"h":800}
},
{
	"filename": "FailBoardBtn.png",
	"frame": {"x":265,"y":1,"w":189,"h":48},
	"rotated": false,
	"trimmed": true,
	"spriteSourceSize": {"x":705,"y":446,"w":189,"h":48},
	"sourceSize": {"w":1600,"h":800}
},
{
	"filename": "FailBoardBtnArea.png",
	"frame": {"x":265,"y":101,"w":90,"h":46},
	"rotated": false,
	"trimmed": false,
	"spriteSourceSize": {"x":0,"y":0,"w":90,"h":46},
	"sourceSize": {"w":90,"h":46}
},
{
	"filename": "FailBoardExitBtnHover.png",
	"frame": {"x":265,"y":51,"w":92,"h":48},
	"rotated": false,
	"trimmed": true,
	"spriteSourceSize": {"x":802,"y":446,"w":92,"h":48},
	"sourceSize": {"w":1600,"h":800}
},
{
	"filename": "FailBoardRestartBtnHover.png",
	"frame": {"x":359,"y":51,"w":92,"h":48},
	"rotated": false,
	"trimmed": true,
	"spriteSourceSize": {"x":705,"y":446,"w":92,"h":48},
	"sourceSize": {"w":1600,"h":800}
}],
"meta": {
	"app": "http://www.codeandweb.com/texturepacker",
	"version": "1.0",
	"image": "FailBoard.png",
	"format": "RGBA8888",
	"size": {"w":455,"h":252},
	"scale": "1",
	"smartupdate": "$TexturePacker:SmartUpdate:1e6b756f6815128c0fd868ce806842fb:7fb6417dfcb50f6ec99c8855d4c140dc:518a81428194c939ee4ded9d72a204c9$"
}
}
